odoo10_addon_account_partner_reconcile-10.0.1.0.0-py2.7-nspkg.pth
odoo/addons/account_partner_reconcile/README.rst
odoo/addons/account_partner_reconcile/__init__.py
odoo/addons/account_partner_reconcile/__manifest__.py
odoo/addons/account_partner_reconcile/models/__init__.py
odoo/addons/account_partner_reconcile/models/res_partner.py
odoo/addons/account_partner_reconcile/static/description/icon.png
odoo/addons/account_partner_reconcile/tests/__init__.py
odoo/addons/account_partner_reconcile/tests/test_account_partner_reconcile.py
odoo/addons/account_partner_reconcile/views/res_partner_view.xml
odoo10_addon_account_partner_reconcile-10.0.1.0.0.dist-info/DESCRIPTION.rst
odoo10_addon_account_partner_reconcile-10.0.1.0.0.dist-info/METADATA
odoo10_addon_account_partner_reconcile-10.0.1.0.0.dist-info/RECORD
odoo10_addon_account_partner_reconcile-10.0.1.0.0.dist-info/WHEEL
odoo10_addon_account_partner_reconcile-10.0.1.0.0.dist-info/metadata.json
odoo10_addon_account_partner_reconcile-10.0.1.0.0.dist-info/namespace_packages.txt
odoo10_addon_account_partner_reconcile-10.0.1.0.0.dist-info/top_level.txt
